Metadata-Version: 2.1
Name: DrissionPage-0518
Version: 4.0.4.21
Summary: Python based web automation tool. It can control the browser and send and receive data packets.
Home-page: https://gitee.com/g1879/DrissionPage
Author: g1879
Author-email: g1879@qq.com
License: BSD
Keywords: DrissionPage
Classifier: Programming Language :: Python :: 3.6
Classifier: Development Status :: 4 - Beta
Classifier: Topic :: Utilities
Classifier: License :: OSI Approved :: BSD License
Requires-Python: >=3.6
License-File: LICENSE
Requires-Dist: lxml
Requires-Dist: requests
Requires-Dist: cssselect
Requires-Dist: DownloadKit >=2.0.0
Requires-Dist: websocket-client
Requires-Dist: click
Requires-Dist: tldextract
Requires-Dist: psutil
